{"cameraMode":{"drawMode":0,"name":"Shaded","section":"Shading Mode"},"sceneLighting":true,"audioPlay":false,"sceneViewState":{"showFog":true,"showMaterialUpdate":false,"showSkybox":true,"showFlares":true,"showImageEffects":true,"showParticleSystems":true,"showVisualEffectGraphs":true,"m_FxEnabled":true},"in2DMode":false,"pivot":{"x":388.8565673828125,"y":1.572445034980774,"z":444.7021789550781},"rotation":{"x":0.06975235790014267,"y":0.6619192957878113,"z":-0.061514850705862048,"w":0.74378502368927},"size":4.177480697631836,"orthographic":false}